{
  "args": {
    "npz": ".\\data\\processed\\seq_MSFT_GOOGL_TSLA_h10_L30.npz",
    "out_dir": "runs\\lstm_20250924_230627",
    "hidden": 96,
    "layers": 2,
    "bidir": true,
    "dropout": 0.3,
    "fc_hidden": 64,
    "epochs": 60,
    "batch": 256,
    "lr": 0.0005,
    "weight_decay": 1e-05,
    "patience": 10,
    "seed": 42,
    "device": "auto"
  },
  "shapes": {
    "X_train": [
      5658,
      30,
      12
    ],
    "X_val": [
      924,
      30,
      12
    ],
    "X_test": [
      1101,
      30,
      12
    ]
  },
  "final_metrics": {
    "train": {
      "loss": 0.63201744141786,
      "acc": 0.6339696005655708,
      "precision": 0.6361556064073226,
      "recall": 0.9047337278106509,
      "f1": 0.7470379870526445,
      "auc": 0.6555948070299391
    },
    "val": {
      "loss": 0.7870535552501678,
      "acc": 0.49783549783549785,
      "precision": 0.5991561181434599,
      "recall": 0.5089605734767025,
      "f1": 0.5503875968992248,
      "auc": 0.5084195115263334
    },
    "test": {
      "loss": 0.9152031064033508,
      "acc": 0.4514078110808356,
      "precision": 0.6140350877192983,
      "recall": 0.16329704510108864,
      "f1": 0.257985257985258,
      "auc": 0.5520655768878143
    }
  },
  "confusion_matrix_test": [
    [
      392,
      66
    ],
    [
      538,
      105
    ]
  ],
  "best_val_f1": 0.6995515695067265
}